agentrix/JsonParser.py
agentrix/__init__.py
agentrix/core.py
agentrix/redisModule.py
agentrix/webScraper.py
agentrix-0.1.2.dist-info/METADATA
agentrix-0.1.2.dist-info/WHEEL
agentrix-0.1.2.dist-info/top_level.txt
agentrix-0.1.2.dist-info/RECORD
