Metadata-Version: 2.4
Name: agentrix
Version: 0.1.2
Summary: A framework for creating AI agents, agent managers and Memory stores (buffer memory and Redis memory store).
Home-page: https://github.com/sanjeev-0407/Agentic.git
Author: Sanjeev
Author-email: sanjeevsaritha03@gmail.com
Classifier: Programming Language :: Python :: 3
Classifier: License :: OSI Approved :: MIT License
Classifier: Operating System :: OS Independent
Requires-Python: >=3.6
Requires-Dist: beautifulsoup4
Requires-Dist: requests
Dynamic: author
Dynamic: author-email
Dynamic: classifier
Dynamic: description
Dynamic: description-content-type
Dynamic: home-page
Dynamic: requires-dist
Dynamic: requires-python
Dynamic: summary
